py_ble_manager/__init__.py
py_ble_manager/adapter/BleAdapter.py
py_ble_manager/adapter/__init__.py
py_ble_manager/ble_api/BleApiBase.py
py_ble_manager/ble_api/BleAtt.py
py_ble_manager/ble_api/BleCommon.py
py_ble_manager/ble_api/BleCommonApi.py
py_ble_manager/ble_api/BleConfig.py
py_ble_manager/ble_api/BleConvert.py
py_ble_manager/ble_api/BleGap.py
py_ble_manager/ble_api/BleGapApi.py
py_ble_manager/ble_api/BleGatt.py
py_ble_manager/ble_api/BleGattc.py
py_ble_manager/ble_api/BleGattcApi.py
py_ble_manager/ble_api/BleGatts.py
py_ble_manager/ble_api/BleGattsApi.py
py_ble_manager/ble_api/BleStorageApi.py
py_ble_manager/ble_api/BleUtil.py
py_ble_manager/ble_api/BleUuid.py
py_ble_manager/ble_api/__init__.py
py_ble_manager/ble_devices/BleCentral.py
py_ble_manager/ble_devices/BleDeviceBase.py
py_ble_manager/ble_devices/BlePeripheral.py
py_ble_manager/ble_devices/__init__.py
py_ble_manager/firmware/da14531_pro_kit_1000000_baud.bin
py_ble_manager/firmware/da1469x_pro_kit_1000000_baud.bin
py_ble_manager/firmware/da1469x_pro_kit_3000000_baud.bin
py_ble_manager/gtl_messages/__init__.py
py_ble_manager/gtl_messages/gapc_message_factory.py
py_ble_manager/gtl_messages/gapm_message_factory.py
py_ble_manager/gtl_messages/gattc_message_factory.py
py_ble_manager/gtl_messages/gattm_message_factory.py
py_ble_manager/gtl_messages/gtl_message_base.py
py_ble_manager/gtl_messages/gtl_message_factory.py
py_ble_manager/gtl_messages/gtl_message_gapc.py
py_ble_manager/gtl_messages/gtl_message_gapm.py
py_ble_manager/gtl_messages/gtl_message_gattc.py
py_ble_manager/gtl_messages/gtl_message_gattm.py
py_ble_manager/gtl_port/__init__.py
py_ble_manager/gtl_port/att.py
py_ble_manager/gtl_port/attm.py
py_ble_manager/gtl_port/co_bt.py
py_ble_manager/gtl_port/co_error.py
py_ble_manager/gtl_port/co_version.py
py_ble_manager/gtl_port/gap.py
py_ble_manager/gtl_port/gapc.py
py_ble_manager/gtl_port/gapc_task.py
py_ble_manager/gtl_port/gapm_task.py
py_ble_manager/gtl_port/gattc_task.py
py_ble_manager-1.0.0.dist-info/LICENSE.txt
py_ble_manager-1.0.0.dist-info/METADATA
py_ble_manager-1.0.0.dist-info/WHEEL
py_ble_manager-1.0.0.dist-info/entry_points.txt
py_ble_manager-1.0.0.dist-info/top_level.txt
py_ble_manager-1.0.0.dist-info/RECORD
