Metadata-Version: 2.1
Name: py-ble-manager
Version: 1.0.0
Summary: A python library for controlling Renesas BLE devices
Author-email: Patrick Murphy <patrick.murphy.jy@renesas.com>
License: The MIT License (MIT)
Project-URL: documentation, https://lpccs-docs.renesas.com/py_ble_manager/index.html
Project-URL: repository, https://github.com/dialog-semiconductor/py_ble_manager
Keywords: ble,bluetooth
Classifier: Programming Language :: Python :: 3
Classifier: Operating System :: OS Independent
Requires-Python: >=3.10.5
License-File: LICENSE.txt
Requires-Dist: pyserial >=3.5
Requires-Dist: ezFlashCLI >=1.0.18
Provides-Extra: dev
Requires-Dist: prompt-toolkit >=3.0.38 ; extra == 'dev'
